sql_constructor/__init__.py
sql_constructor/constants.py
sql_constructor/helpers.py
sql_constructor/sql_container.py
sql_constructor/sql_cte.py
sql_constructor/sql_query.py
sql_constructor/sql_section.py
sql_constructor-1.0.13.dist-info/LICENSE
sql_constructor-1.0.13.dist-info/METADATA
sql_constructor-1.0.13.dist-info/WHEEL
sql_constructor-1.0.13.dist-info/top_level.txt
sql_constructor-1.0.13.dist-info/RECORD
