Metadata-Version: 2.1
Name: sql-constructor
Version: 1.0.13
Summary: Let you build SQL requests in pythonic way. SQL blocks could be nested and flexible as you want it to be, constructed dynamically and looks pretty! You could also build request once and cache it (but still use variables to replace dynamically). Solid solution!
Author-email: Andrey Smirnov <abc-sm@yandex.ru>
Project-URL: Homepage, https://github.com/akvilary/sql_constructor
Project-URL: Bug Tracker, https://github.com/akvilary/sql_constructor/issues
Classifier: Programming Language :: Python :: 3
Classifier: License :: OSI Approved :: MIT License
Classifier: Operating System :: OS Independent
Requires-Python: >=3.7
License-File: LICENSE
